corradjust/__init__.py
corradjust/corradjust.py
corradjust/metrics.py
corradjust/plots.py
corradjust/tests/generate_test_data.py
corradjust/tests/test_corradjust.py
corradjust/tests/test_data/corradjust_output/corr_distr.test_samples.all_pairs.png
corradjust/tests/test_data/corradjust_output/corr_distr.test_samples.training_pairs.png
corradjust/tests/test_data/corradjust_output/corr_distr.test_samples.validation_pairs.png
corradjust/tests/test_data/corradjust_output/corr_distr.training_samples.all_pairs.png
corradjust/tests/test_data/corradjust_output/corr_distr.training_samples.training_pairs.png
corradjust/tests/test_data/corradjust_output/corr_distr.training_samples.validation_pairs.png
corradjust/tests/test_data/corradjust_output/corrs.test_samples.tsv.gz
corradjust/tests/test_data/corradjust_output/corrs.training_samples.tsv.gz
corradjust/tests/test_data/corradjust_output/data_clean.test_samples.tsv
corradjust/tests/test_data/corradjust_output/data_clean.training_samples.tsv
corradjust/tests/test_data/corradjust_output/fit.all_samp.png
corradjust/tests/test_data/corradjust_output/fit.tsv
corradjust/tests/test_data/corradjust_output/scores/test_samples.all_pairs.Clean.tsv
corradjust/tests/test_data/corradjust_output/scores/test_samples.all_pairs.Raw.tsv
corradjust/tests/test_data/corradjust_output/scores/test_samples.training_pairs.Clean.tsv
corradjust/tests/test_data/corradjust_output/scores/test_samples.training_pairs.Raw.tsv
corradjust/tests/test_data/corradjust_output/scores/test_samples.validation_pairs.Clean.tsv
corradjust/tests/test_data/corradjust_output/scores/test_samples.validation_pairs.Raw.tsv
corradjust/tests/test_data/corradjust_output/scores/training_samples.all_pairs.Clean.tsv
corradjust/tests/test_data/corradjust_output/scores/training_samples.all_pairs.Raw.tsv
corradjust/tests/test_data/corradjust_output/scores/training_samples.training_pairs.Clean.tsv
corradjust/tests/test_data/corradjust_output/scores/training_samples.training_pairs.Raw.tsv
corradjust-1.0.1.dist-info/LICENSE
corradjust-1.0.1.dist-info/METADATA
corradjust-1.0.1.dist-info/WHEEL
corradjust-1.0.1.dist-info/RECORD
